{
    "data": [
      {
        "src": "https://scontent.fhan3-1.fna.fbcdn.net/v/t39.30808-6/335014554_1920132098352294_7205002077998324848_n.jpg?_nc_cat=102&ccb=1-7&_nc_sid=730e14&_nc_ohc=Xue4aHfmD6kAX8ZAWxV&_nc_ht=scontent.fhan3-1.fna&oh=00_AfB8_05av1e_ugN0rKcVYmf40Ma0eeNYIff8wIDFsJRiKw&oe=640B38CB",
        "name": "Chiiu",
        "title": "Gái hiện đại không ngại độc thân"
      },
      {
        "src": "https://scontent.fhan3-2.fna.fbcdn.net/v/t39.30808-6/335015254_717023336772429_789508578738021695_n.jpg?_nc_cat=107&ccb=1-7&_nc_sid=730e14&_nc_ohc=ig5H5cY6zg0AX_DyEDA&_nc_ht=scontent.fhan3-2.fna&oh=00_AfDnfOJnb3JQC9QuodZL5s0P0uIseuu6KPS6LPKEhb466g&oe=640CF36F",
        "name": "Hiền Linh",
        "title": "Phụ nữ VTI hiện đại cần không ngừng học tập, hoàn thiện bản thân, sống với cá tính, đam mê của mình. Mỗi chúng ta là một bông hoa đẹp nhất, hãy sống là chính mình, bình thường nhưng không tầm thường!"
      },
      {
        "src": "https://scontent.fhan4-3.fna.fbcdn.net/v/t39.30808-6/334980651_933093847725519_9017710110124461347_n.jpg?_nc_cat=103&ccb=1-7&_nc_sid=730e14&_nc_ohc=vaYQCtly4wIAX8uLx5m&_nc_ht=scontent.fhan4-3.fna&oh=00_AfBe6VXuSTYG2EpbEMcnSL0bqgGLqyAm2ngXZBjHU8Wf1w&oe=640B0D86",
        "name": "Quỳnh Ngân",
        "title": "Đến với nhau là một sự khởi đầu. Giữ được nhau là sự tiến triển. Làm việc cùng nhau là sự thành công."
      }
    ],
    "time": "17:00:00 08/03/2023"
  }
  
